df_query/__init__.py
df_query/cli.py
df_query/df_query.py
df_query/query_context.py
df_query-0.1.0.dist-info/AUTHORS.rst
df_query-0.1.0.dist-info/LICENSE
df_query-0.1.0.dist-info/METADATA
df_query-0.1.0.dist-info/WHEEL
df_query-0.1.0.dist-info/entry_points.txt
df_query-0.1.0.dist-info/top_level.txt
df_query-0.1.0.dist-info/RECORD
