Metadata-Version: 2.1
Name: df-query
Version: 0.1.0
Summary: A Pandas DataFrame SQL Query Utility
Home-page: https://github.com/rjdscott/df_query
Author: Rob Scott
Author-email: rob@rjdscott.com
License: MIT license
Keywords: df_query
Platform: UNKNOWN
Classifier: Development Status :: 2 - Pre-Alpha
Classifier: Intended Audience :: Developers
Classifier: License :: OSI Approved :: MIT License
Classifier: Natural Language :: English
Classifier: Programming Language :: Python :: 3
Classifier: Programming Language :: Python :: 3.6
Classifier: Programming Language :: Python :: 3.7
Classifier: Programming Language :: Python :: 3.8
Requires-Python: >=3.6
Requires-Dist: pandas
